<?xml version="1.0" encoding="utf-8"?>
<xliff xmlns="urn:oasis:names:tc:xliff:document:1.2" xmlns:xsi="http://www.w3.org/2001/XMLSchema-instance" version="1.2" xsi:schemaLocation="urn:oasis:names:tc:xliff:document:1.2 xliff-core-1.2-transitional.xsd">
  <file datatype="xml" original="HtmlImage.xml" source-language="en-US" target-language="it-IT">
    <header>
      <tool tool-id="mdxliff" tool-name="mdxliff" tool-version="1.0-15c36f0" tool-company="Microsoft" />
      <xliffext:skl_file_name xmlns:xliffext="urn:microsoft:content:schema:xliffextensions">02cd5861-7ce2-4a82-b358-31f8435a0ac5631e562efbad52dcef21f9bdca474ca0bc8cf153.skl</xliffext:skl_file_name>
      <xliffext:version xmlns:xliffext="urn:microsoft:content:schema:xliffextensions">1.2</xliffext:version>
      <xliffext:ms.openlocfilehash xmlns:xliffext="urn:microsoft:content:schema:xliffextensions">631e562efbad52dcef21f9bdca474ca0bc8cf153</xliffext:ms.openlocfilehash>
      <xliffext:ms.sourcegitcommit xmlns:xliffext="urn:microsoft:content:schema:xliffextensions">d31dc2ede16f6f7bc64e90d9f897ff54c4e3869b</xliffext:ms.sourcegitcommit>
      <xliffext:ms.lasthandoff xmlns:xliffext="urn:microsoft:content:schema:xliffextensions">04/03/2018</xliffext:ms.lasthandoff>
      <xliffext:moniker_ids xmlns:xliffext="urn:microsoft:content:schema:xliffextensions">netframework-4.5.1,netframework-4.5.2,netframework-4.5,netframework-4.6.1,netframework-4.6.2,netframework-4.6,netframework-4.7.1,netframework-4.7</xliffext:moniker_ids>
    </header>
    <body>
      <group id="content" extype="content">
        <trans-unit id="101" translate="yes" xml:space="preserve" uid="T:System.Web.UI.HtmlControls.HtmlImage">
          <source>Provides programmatic access for the HTML <ph id="ph1">&lt;see langword="&amp;lt;img&amp;gt;" /&gt;</ph> element on the server.</source>
          <target state="translated">Fornisce accesso a livello di codice all'elemento HTML <ph id="ph1">&lt;see langword="&amp;lt;img&amp;gt;" /&gt;</ph> sul server.</target>       </trans-unit>
        <trans-unit id="102" translate="yes" xml:space="preserve" extradata="MT" uid="T:System.Web.UI.HtmlControls.HtmlImage">
          <source>Use this control to display an image on a Web page.</source>
          <target state="translated">Utilizzare questo controllo per visualizzare un'immagine in una pagina Web.</target>       </trans-unit>
        <trans-unit id="103" translate="yes" xml:space="preserve" extradata="MT" uid="T:System.Web.UI.HtmlControls.HtmlImage">
          <source>The <ph id="ph1">&lt;xref:System.Web.UI.HtmlControls.HtmlImage&gt;</ph> control can be programmatically manipulated to change the image displayed, the image size, and the alignment of the image relative to other page elements.</source>
          <target state="translated">Il <ph id="ph1">&lt;xref:System.Web.UI.HtmlControls.HtmlImage&gt;</ph> controllo può essere modificato a livello di codice per modificare l'immagine visualizzata, le dimensioni dell'immagine e l'allineamento dell'immagine rispetto agli altri elementi di pagina.</target>       </trans-unit>
        <trans-unit id="104" translate="yes" xml:space="preserve" extradata="MT" uid="T:System.Web.UI.HtmlControls.HtmlImage">
          <source>For a list of initial property values for an instance of <ph id="ph1">&lt;xref:System.Web.UI.HtmlControls.HtmlImage&gt;</ph>, see the <ph id="ph2">&lt;xref:System.Web.UI.HtmlControls.HtmlImage.%23ctor%2A&gt;</ph> constructor.</source>
          <target state="translated">Per un elenco di valori di proprietà iniziali per un'istanza di <ph id="ph1">&lt;xref:System.Web.UI.HtmlControls.HtmlImage&gt;</ph>, vedere il <ph id="ph2">&lt;xref:System.Web.UI.HtmlControls.HtmlImage.%23ctor%2A&gt;</ph> costruttore.</target>       </trans-unit>
        <trans-unit id="105" translate="yes" xml:space="preserve" extradata="MT" uid="T:System.Web.UI.HtmlControls.HtmlImage">
          <source>The following code example demonstrates how to programmatically modify the properties of an <ph id="ph1">&lt;xref:System.Web.UI.HtmlControls.HtmlImage&gt;</ph> control when an <ph id="ph2">&lt;xref:System.Web.UI.HtmlControls.HtmlButton&gt;</ph> is clicked.</source>
          <target state="translated">Esempio di codice riportato di seguito viene illustrato come modificare a livello di codice le proprietà di un <ph id="ph1">&lt;xref:System.Web.UI.HtmlControls.HtmlImage&gt;</ph> controllare quando un <ph id="ph2">&lt;xref:System.Web.UI.HtmlControls.HtmlButton&gt;</ph> si fa clic.</target>       </trans-unit>
        <trans-unit id="106" translate="yes" xml:space="preserve" uid="M:System.Web.UI.HtmlControls.HtmlImage.#ctor">
          <source>Initializes a new instance of the <ph id="ph1">&lt;see cref="T:System.Web.UI.HtmlControls.HtmlImage" /&gt;</ph> class.</source>
          <target state="translated">Inizializza una nuova istanza della classe <ph id="ph1">&lt;see cref="T:System.Web.UI.HtmlControls.HtmlImage" /&gt;</ph>.</target>       </trans-unit>
        <trans-unit id="107" translate="yes" xml:space="preserve" extradata="MT" uid="M:System.Web.UI.HtmlControls.HtmlImage.#ctor">
          <source>Use this constructor to create and initialize a new instance of the <ph id="ph1">&lt;xref:System.Web.UI.HtmlControls.HtmlImage&gt;</ph> class.</source>
          <target state="translated">Utilizzare questo costruttore per creare e inizializzare una nuova istanza di <ph id="ph1">&lt;xref:System.Web.UI.HtmlControls.HtmlImage&gt;</ph> classe.</target>       </trans-unit>
        <trans-unit id="108" translate="yes" xml:space="preserve" extradata="MT" uid="M:System.Web.UI.HtmlControls.HtmlImage.#ctor">
          <source>The following table shows the initial property value for an instance of <ph id="ph1">&lt;xref:System.Web.UI.HtmlControls.HtmlImage&gt;</ph>.</source>
          <target state="translated">Nella tabella seguente mostra il valore di proprietà iniziali per un'istanza di <ph id="ph1">&lt;xref:System.Web.UI.HtmlControls.HtmlImage&gt;</ph>.</target>       </trans-unit>
        <trans-unit id="109" translate="yes" xml:space="preserve" extradata="MT" uid="M:System.Web.UI.HtmlControls.HtmlImage.#ctor">
          <source>Property</source>
          <target state="translated">Proprietà</target>       </trans-unit>
        <trans-unit id="110" translate="yes" xml:space="preserve" extradata="MT" uid="M:System.Web.UI.HtmlControls.HtmlImage.#ctor">
          <source>Initial Value</source>
          <target state="translated">Valore iniziale</target>       </trans-unit>
        <trans-unit id="111" translate="yes" xml:space="preserve" extradata="MT" uid="M:System.Web.UI.HtmlControls.HtmlImage.#ctor">
          <source>The "img" literal string.</source>
          <target state="translated">La stringa letterale "img".</target>       </trans-unit>
        <trans-unit id="112" translate="yes" xml:space="preserve" extradata="MT" uid="M:System.Web.UI.HtmlControls.HtmlImage.#ctor">
          <source>The following code example illustrates how to create and initialize a new instance of the <ph id="ph1">&lt;xref:System.Web.UI.HtmlControls.HtmlImage&gt;</ph> control.</source>
          <target state="translated">Esempio di codice seguente viene illustrato come creare e inizializzare una nuova istanza di <ph id="ph1">&lt;xref:System.Web.UI.HtmlControls.HtmlImage&gt;</ph> controllo.</target>       </trans-unit>
        <trans-unit id="113" translate="yes" xml:space="preserve" uid="P:System.Web.UI.HtmlControls.HtmlImage.Align">
          <source>Gets or sets the alignment of the image relative to other Web page elements.</source>
          <target state="translated">Ottiene o imposta l'allineamento dell'immagine in relazione ad altri elementi della pagina Web.</target>       </trans-unit>
        <trans-unit id="114" translate="yes" xml:space="preserve" extradata="MT" uid="P:System.Web.UI.HtmlControls.HtmlImage.Align">
          <source>A string that specifies the alignment of the image relative to other Web page elements.</source>
          <target state="translated">Stringa che specifica l'allineamento dell'immagine in relazione ad altri elementi della pagina Web.</target>       </trans-unit>
        <trans-unit id="115" translate="yes" xml:space="preserve" extradata="MT" uid="P:System.Web.UI.HtmlControls.HtmlImage.Align">
          <source>Use this property to specify the alignment of the image with respect to other elements on the Web page.</source>
          <target state="translated">Utilizzare questa proprietà per specificare l'allineamento dell'immagine rispetto a altro elementi della pagina Web.</target>       </trans-unit>
        <trans-unit id="116" translate="yes" xml:space="preserve" extradata="MT" uid="P:System.Web.UI.HtmlControls.HtmlImage.Align">
          <source>The following table represents the possible values.</source>
          <target state="translated">Nella tabella seguente rappresenta i valori possibili.</target>       </trans-unit>
        <trans-unit id="117" translate="yes" xml:space="preserve" extradata="MT" uid="P:System.Web.UI.HtmlControls.HtmlImage.Align">
          <source>Value</source>
          <target state="translated">Valore</target>       </trans-unit>
        <trans-unit id="118" translate="yes" xml:space="preserve" extradata="MT" uid="P:System.Web.UI.HtmlControls.HtmlImage.Align">
          <source>Description</source>
          <target state="translated">Descrizione</target>       </trans-unit>
        <trans-unit id="119" translate="yes" xml:space="preserve" extradata="MT" uid="P:System.Web.UI.HtmlControls.HtmlImage.Align">
          <source>left</source>
          <target state="translated">left</target>       </trans-unit>
        <trans-unit id="120" translate="yes" xml:space="preserve" extradata="MT" uid="P:System.Web.UI.HtmlControls.HtmlImage.Align">
          <source>The image is aligned on the left side of the Web page.</source>
          <target state="translated">L'immagine è allineato a sinistra della pagina Web.</target>       </trans-unit>
        <trans-unit id="121" translate="yes" xml:space="preserve" extradata="MT" uid="P:System.Web.UI.HtmlControls.HtmlImage.Align">
          <source>center</source>
          <target state="translated">Center</target>       </trans-unit>
        <trans-unit id="122" translate="yes" xml:space="preserve" extradata="MT" uid="P:System.Web.UI.HtmlControls.HtmlImage.Align">
          <source>The image is aligned in the center of the Web page.</source>
          <target state="translated">L'immagine è allineato al centro della pagina Web.</target>       </trans-unit>
        <trans-unit id="123" translate="yes" xml:space="preserve" extradata="MT" uid="P:System.Web.UI.HtmlControls.HtmlImage.Align">
          <source>right</source>
          <target state="translated">right</target>       </trans-unit>
        <trans-unit id="124" translate="yes" xml:space="preserve" extradata="MT" uid="P:System.Web.UI.HtmlControls.HtmlImage.Align">
          <source>The image is aligned on the right side of the Web page.</source>
          <target state="translated">L'immagine è allineato a destra della pagina Web.</target>       </trans-unit>
        <trans-unit id="125" translate="yes" xml:space="preserve" extradata="MT" uid="P:System.Web.UI.HtmlControls.HtmlImage.Align">
          <source>top</source>
          <target state="translated">top</target>       </trans-unit>
        <trans-unit id="126" translate="yes" xml:space="preserve" extradata="MT" uid="P:System.Web.UI.HtmlControls.HtmlImage.Align">
          <source>Other elements in the Web page are aligned with the top edge of the image.</source>
          <target state="translated">Altri elementi nella pagina Web sono allineati al bordo superiore dell'immagine.</target>       </trans-unit>
        <trans-unit id="127" translate="yes" xml:space="preserve" extradata="MT" uid="P:System.Web.UI.HtmlControls.HtmlImage.Align">
          <source>middle</source>
          <target state="translated">intermedio</target>       </trans-unit>
        <trans-unit id="128" translate="yes" xml:space="preserve" extradata="MT" uid="P:System.Web.UI.HtmlControls.HtmlImage.Align">
          <source>Other elements in the Web page are aligned with the middle of the image.</source>
          <target state="translated">Altri elementi nella pagina Web sono allineate al centro dell'immagine.</target>       </trans-unit>
        <trans-unit id="129" translate="yes" xml:space="preserve" extradata="MT" uid="P:System.Web.UI.HtmlControls.HtmlImage.Align">
          <source>bottom</source>
          <target state="translated">bottom</target>       </trans-unit>
        <trans-unit id="130" translate="yes" xml:space="preserve" extradata="MT" uid="P:System.Web.UI.HtmlControls.HtmlImage.Align">
          <source>Other elements in the Web page are aligned with the bottom edge of the image.</source>
          <target state="translated">Gli altri elementi nella pagina Web sono allineati al bordo inferiore dell'immagine.</target>       </trans-unit>
        <trans-unit id="131" translate="yes" xml:space="preserve" extradata="MT" uid="P:System.Web.UI.HtmlControls.HtmlImage.Align">
          <source>The center value might not work on all browsers.</source>
          <target state="translated">Il valore center potrebbe non funzionare per tutti i browser.</target>       </trans-unit>
        <trans-unit id="132" translate="yes" xml:space="preserve" extradata="MT" uid="P:System.Web.UI.HtmlControls.HtmlImage.Align">
          <source>To center an image, wrap the <ph id="ph1">&lt;xref:System.Web.UI.HtmlControls.HtmlImage&gt;</ph> control inside paragraph tags that contain the <ph id="ph2">`align`</ph> attribute set to <ph id="ph3">`"center"`</ph> (<ph id="ph4">`&lt;p align= "center"&gt;`</ph>).</source>
          <target state="translated">Per centrare un'immagine, eseguire il wrapping di <ph id="ph1">&lt;xref:System.Web.UI.HtmlControls.HtmlImage&gt;</ph> controllo all'interno di tag di paragrafo contenenti il <ph id="ph2">`align`</ph> attributo impostato su <ph id="ph3">`"center"`</ph> (<ph id="ph4">`&lt;p align= "center"&gt;`</ph>).</target>       </trans-unit>
        <trans-unit id="133" translate="yes" xml:space="preserve" extradata="MT" uid="P:System.Web.UI.HtmlControls.HtmlImage.Align">
          <source>The following code example demonstrates how to use the <ph id="ph1">&lt;xref:System.Web.UI.HtmlControls.HtmlImage.Align%2A&gt;</ph> property to specify the alignment of an image on a Web page.</source>
          <target state="translated">Esempio di codice seguente viene illustrato come utilizzare il <ph id="ph1">&lt;xref:System.Web.UI.HtmlControls.HtmlImage.Align%2A&gt;</ph> proprietà per specificare l'allineamento di un'immagine in una pagina Web.</target>       </trans-unit>
        <trans-unit id="134" translate="yes" xml:space="preserve" extradata="MT" uid="P:System.Web.UI.HtmlControls.HtmlImage.Align">
          <source>The following code example demonstrates how to center an image on the Web page by wrapping the <ph id="ph1">&lt;xref:System.Web.UI.HtmlControls.HtmlImage&gt;</ph> control inside paragraph tags with the <ph id="ph2">`align`</ph> attribute set to <ph id="ph3">`"center"`</ph>.</source>
          <target state="translated">Esempio di codice seguente viene illustrato come allineare al centro di un'immagine della pagina Web eseguendo il wrapping di <ph id="ph1">&lt;xref:System.Web.UI.HtmlControls.HtmlImage&gt;</ph> controllo all'interno di tag di paragrafo con il <ph id="ph2">`align`</ph> attributo impostato su <ph id="ph3">`"center"`</ph>.</target>       </trans-unit>
        <trans-unit id="135" translate="yes" xml:space="preserve" uid="P:System.Web.UI.HtmlControls.HtmlImage.Alt">
          <source>Gets or sets the alternative caption the browser displays if an image is unavailable or currently downloading and not yet finished.</source>
          <target state="translated">Ottiene o imposta la didascalia alternativa visualizzata nel browser se una immagine non è disponibile o se il relativo download non è ancora terminato.</target>       </trans-unit>
        <trans-unit id="136" translate="yes" xml:space="preserve" extradata="MT" uid="P:System.Web.UI.HtmlControls.HtmlImage.Alt">
          <source>A string that contains the alternative caption for the browser to use when the image is unavailable.</source>
          <target state="translated">Stringa che contiene la didascalia alternativa utilizzata dal browser quando l'immagine non è disponibile.</target>       </trans-unit>
        <trans-unit id="137" translate="yes" xml:space="preserve" extradata="MT" uid="P:System.Web.UI.HtmlControls.HtmlImage.Alt">
          <source>Use this property to specify the caption displayed when the image specified by the <ph id="ph1">&lt;xref:System.Web.UI.HtmlControls.HtmlImage.Src%2A&gt;</ph> property is unavailable.</source>
          <target state="translated">Utilizzare questa proprietà per specificare la didascalia visualizzata quando l'immagine specificata per il <ph id="ph1">&lt;xref:System.Web.UI.HtmlControls.HtmlImage.Src%2A&gt;</ph> proprietà non è disponibile.</target>       </trans-unit>
        <trans-unit id="138" translate="yes" xml:space="preserve" extradata="MT" uid="P:System.Web.UI.HtmlControls.HtmlImage.Alt">
          <source>On newer browsers, this caption also appears as a ToolTip.</source>
          <target state="translated">Nei browser più recenti questa didascalia viene visualizzata anche come descrizione comando.</target>       </trans-unit>
        <trans-unit id="139" translate="yes" xml:space="preserve" extradata="MT" uid="P:System.Web.UI.HtmlControls.HtmlImage.Alt">
          <source>The following code example demonstrates how to use the <ph id="ph1">&lt;xref:System.Web.UI.HtmlControls.HtmlImage.Alt%2A&gt;</ph> property to specify the caption to display when the image specified by the <ph id="ph2">&lt;xref:System.Web.UI.HtmlControls.HtmlImage.Src%2A&gt;</ph> property is unavailable.</source>
          <target state="translated">Esempio di codice seguente viene illustrato come utilizzare il <ph id="ph1">&lt;xref:System.Web.UI.HtmlControls.HtmlImage.Alt%2A&gt;</ph> proprietà per specificare la didascalia da visualizzare quando l'immagine specificata per il <ph id="ph2">&lt;xref:System.Web.UI.HtmlControls.HtmlImage.Src%2A&gt;</ph> proprietà non è disponibile.</target>       </trans-unit>
        <trans-unit id="140" translate="yes" xml:space="preserve" uid="P:System.Web.UI.HtmlControls.HtmlImage.Border">
          <source>Gets or sets the width of a frame for an image.</source>
          <target state="translated">Ottiene o imposta la larghezza di un frame per un'immagine.</target>       </trans-unit>
        <trans-unit id="141" translate="yes" xml:space="preserve" extradata="MT" uid="P:System.Web.UI.HtmlControls.HtmlImage.Border">
          <source>The width (in pixels) of a frame for an image.</source>
          <target state="translated">Larghezza in pixel di un frame per un'immagine.</target>       </trans-unit>
        <trans-unit id="142" translate="yes" xml:space="preserve" extradata="MT" uid="P:System.Web.UI.HtmlControls.HtmlImage.Border">
          <source>Use this property to create a frame with the specified width (in pixels) for an image.</source>
          <target state="translated">Utilizzare questa proprietà per creare un frame con la larghezza specificata, in pixel, per un'immagine.</target>       </trans-unit>
        <trans-unit id="143" translate="yes" xml:space="preserve" extradata="MT" uid="P:System.Web.UI.HtmlControls.HtmlImage.Border">
          <source>The following code example demonstrates how to use the <ph id="ph1">&lt;xref:System.Web.UI.HtmlControls.HtmlImage.Border%2A&gt;</ph> property to specify a frame with a width of 5 pixels for an <ph id="ph2">&lt;xref:System.Web.UI.HtmlControls.HtmlImage&gt;</ph> control.</source>
          <target state="translated">Esempio di codice seguente viene illustrato come utilizzare il <ph id="ph1">&lt;xref:System.Web.UI.HtmlControls.HtmlImage.Border%2A&gt;</ph> proprietà per specificare un frame con una larghezza di 5 pixel per un <ph id="ph2">&lt;xref:System.Web.UI.HtmlControls.HtmlImage&gt;</ph> controllo.</target>       </trans-unit>
        <trans-unit id="144" translate="yes" xml:space="preserve" uid="P:System.Web.UI.HtmlControls.HtmlImage.Height">
          <source>Gets or sets the height of the image.</source>
          <target state="translated">Ottiene o imposta l'altezza dell'immagine.</target>       </trans-unit>
        <trans-unit id="145" translate="yes" xml:space="preserve" extradata="MT" uid="P:System.Web.UI.HtmlControls.HtmlImage.Height">
          <source>The height of the image.</source>
          <target state="translated">Altezza dell'immagine.</target>       </trans-unit>
        <trans-unit id="146" translate="yes" xml:space="preserve" extradata="MT" uid="P:System.Web.UI.HtmlControls.HtmlImage.Height">
          <source>The <ph id="ph1">&lt;xref:System.Web.UI.HtmlControls.HtmlImage.Height%2A&gt;</ph> and <ph id="ph2">&lt;xref:System.Web.UI.HtmlControls.HtmlImage.Width%2A&gt;</ph> properties can be used two ways.</source>
          <target state="translated">Il <ph id="ph1">&lt;xref:System.Web.UI.HtmlControls.HtmlImage.Height%2A&gt;</ph> e <ph id="ph2">&lt;xref:System.Web.UI.HtmlControls.HtmlImage.Width%2A&gt;</ph> possono essere utilizzate in due modi.</target>       </trans-unit>
        <trans-unit id="147" translate="yes" xml:space="preserve" extradata="MT" uid="P:System.Web.UI.HtmlControls.HtmlImage.Height">
          <source>You can use the <ph id="ph1">&lt;xref:System.Web.UI.HtmlControls.HtmlImage.Height%2A&gt;</ph> and <ph id="ph2">&lt;xref:System.Web.UI.HtmlControls.HtmlImage.Width%2A&gt;</ph> properties to send image size specifications to the browser.</source>
          <target state="translated">È possibile utilizzare il <ph id="ph1">&lt;xref:System.Web.UI.HtmlControls.HtmlImage.Height%2A&gt;</ph> e <ph id="ph2">&lt;xref:System.Web.UI.HtmlControls.HtmlImage.Width%2A&gt;</ph> le proprietà per inviare le specifiche sulle dimensioni di immagine nel browser.</target>       </trans-unit>
        <trans-unit id="148" translate="yes" xml:space="preserve" extradata="MT" uid="P:System.Web.UI.HtmlControls.HtmlImage.Height">
          <source>This displays the Web page faster because the browser does not need to recalculate the positions of elements on the page when the image loads.</source>
          <target state="translated">Verrà visualizzata la pagina Web più veloce perché non è necessario ricalcolare le posizioni degli elementi nella pagina quando l'immagine viene caricata nel browser.</target>       </trans-unit>
        <trans-unit id="149" translate="yes" xml:space="preserve" extradata="MT" uid="P:System.Web.UI.HtmlControls.HtmlImage.Height">
          <source>You can also use the <ph id="ph1">&lt;xref:System.Web.UI.HtmlControls.HtmlImage.Height%2A&gt;</ph> and <ph id="ph2">&lt;xref:System.Web.UI.HtmlControls.HtmlImage.Width%2A&gt;</ph> properties to scale the image.</source>
          <target state="translated">È inoltre possibile utilizzare il <ph id="ph1">&lt;xref:System.Web.UI.HtmlControls.HtmlImage.Height%2A&gt;</ph> e <ph id="ph2">&lt;xref:System.Web.UI.HtmlControls.HtmlImage.Width%2A&gt;</ph> proprietà per ridimensionare l'immagine.</target>       </trans-unit>
        <trans-unit id="150" translate="yes" xml:space="preserve" extradata="MT" uid="P:System.Web.UI.HtmlControls.HtmlImage.Height">
          <source>When using values different from the physical size of the image, the image is resized accordingly.</source>
          <target state="translated">Quando si utilizzano valori diversi rispetto alle dimensioni fisiche dell'immagine, l'immagine viene ridimensionata di conseguenza.</target>       </trans-unit>
        <trans-unit id="151" translate="yes" xml:space="preserve" extradata="MT" uid="P:System.Web.UI.HtmlControls.HtmlImage.Height">
          <source>However, this method for scaling the image is not recommended because it takes longer for the page to display it.</source>
          <target state="translated">Tuttavia, questo metodo per il ridimensionamento dell'immagine è sconsigliato, perché richiede più tempo per la visualizzazione della pagina.</target>       </trans-unit>
        <trans-unit id="152" translate="yes" xml:space="preserve" extradata="MT" uid="P:System.Web.UI.HtmlControls.HtmlImage.Height">
          <source>Instead, physically resize the image to the size you need.</source>
          <target state="translated">Consiglia di ridimensionare l'immagine per la dimensione che è necessario.</target>       </trans-unit>
        <trans-unit id="153" translate="yes" xml:space="preserve" extradata="MT" uid="P:System.Web.UI.HtmlControls.HtmlImage.Height">
          <source>By default, the <ph id="ph1">&lt;xref:System.Web.UI.HtmlControls.HtmlImage.Height%2A&gt;</ph> property is expressed in pixels, but it can also be expressed as a percentage of the size of the window.</source>
          <target state="translated">Per impostazione predefinita, il <ph id="ph1">&lt;xref:System.Web.UI.HtmlControls.HtmlImage.Height%2A&gt;</ph> espresse in pixel, ma può anche essere espressa come percentuale delle dimensioni della finestra.</target>       </trans-unit>
        <trans-unit id="154" translate="yes" xml:space="preserve" extradata="MT" uid="P:System.Web.UI.HtmlControls.HtmlImage.Height">
          <source>The following code example demonstrates how to use the <ph id="ph1">&lt;xref:System.Web.UI.HtmlControls.HtmlImage.Height%2A&gt;</ph> property to programmatically modify the height of the displayed image.</source>
          <target state="translated">Esempio di codice seguente viene illustrato come utilizzare il <ph id="ph1">&lt;xref:System.Web.UI.HtmlControls.HtmlImage.Height%2A&gt;</ph> proprietà a livello di codice modificare l'altezza dell'immagine visualizzata.</target>       </trans-unit>
        <trans-unit id="155" translate="yes" xml:space="preserve" uid="M:System.Web.UI.HtmlControls.HtmlImage.RenderAttributes(System.Web.UI.HtmlTextWriter)">
          <source>The <ph id="ph1">&lt;see cref="T:System.Web.UI.HtmlTextWriter" /&gt;</ph> that contains the output stream to render on the client.</source>
          <target state="translated">Oggetto <ph id="ph1">&lt;see cref="T:System.Web.UI.HtmlTextWriter" /&gt;</ph> contenente il flusso di output per il rendering sul client.</target>       </trans-unit>
        <trans-unit id="156" translate="yes" xml:space="preserve" uid="M:System.Web.UI.HtmlControls.HtmlImage.RenderAttributes(System.Web.UI.HtmlTextWriter)">
          <source>Renders the <ph id="ph1">&lt;see cref="T:System.Web.UI.HtmlControls.HtmlImage" /&gt;</ph> control's attributes to the specified <ph id="ph2">&lt;see cref="T:System.Web.UI.HtmlTextWriter" /&gt;</ph> object.</source>
          <target state="translated">Esegue il rendering degli attributi del controllo <ph id="ph1">&lt;see cref="T:System.Web.UI.HtmlControls.HtmlImage" /&gt;</ph> nell'oggetto <ph id="ph2">&lt;see cref="T:System.Web.UI.HtmlTextWriter" /&gt;</ph> specificato.</target>       </trans-unit>
        <trans-unit id="157" translate="yes" xml:space="preserve" extradata="MT" uid="M:System.Web.UI.HtmlControls.HtmlImage.RenderAttributes(System.Web.UI.HtmlTextWriter)">
          <source>If the value of the <ph id="ph1">&lt;xref:System.Web.UI.HtmlControls.HtmlImage.Src%2A&gt;</ph> property is a malformed URL, the <ph id="ph2">&lt;xref:System.Web.UI.HtmlControls.HtmlImage.RenderAttributes%2A&gt;</ph> method throws an <ph id="ph3">&lt;xref:System.Web.HttpException&gt;</ph> exception.</source>
          <target state="translated">Se il valore della <ph id="ph1">&lt;xref:System.Web.UI.HtmlControls.HtmlImage.Src%2A&gt;</ph> proprietà è un URL non valido, il <ph id="ph2">&lt;xref:System.Web.UI.HtmlControls.HtmlImage.RenderAttributes%2A&gt;</ph> metodo genera un <ph id="ph3">&lt;xref:System.Web.HttpException&gt;</ph> eccezione.</target>       </trans-unit>
        <trans-unit id="158" translate="yes" xml:space="preserve" extradata="MT" uid="M:System.Web.UI.HtmlControls.HtmlImage.RenderAttributes(System.Web.UI.HtmlTextWriter)">
          <source>The <ph id="ph1">&lt;xref:System.Web.UI.HtmlControls.HtmlImage.RenderAttributes%2A&gt;</ph> method overrides the base class's <ph id="ph2">&lt;xref:System.Web.UI.HtmlControls.HtmlImage.RenderAttributes%2A&gt;</ph> method to write the <ph id="ph3">`src`</ph> attribute of the rendered <ph id="ph4">&lt;xref:System.Web.UI.HtmlControls.HtmlImage&gt;</ph> control.</source>
          <target state="translated">Il <ph id="ph1">&lt;xref:System.Web.UI.HtmlControls.HtmlImage.RenderAttributes%2A&gt;</ph> metodo esegue l'override della classe base <ph id="ph2">&lt;xref:System.Web.UI.HtmlControls.HtmlImage.RenderAttributes%2A&gt;</ph> metodo per scrivere il <ph id="ph3">`src`</ph> attributo dell'oggetto sottoposto a rendering <ph id="ph4">&lt;xref:System.Web.UI.HtmlControls.HtmlImage&gt;</ph> controllo.</target>       </trans-unit>
        <trans-unit id="159" translate="yes" xml:space="preserve" extradata="MT" uid="M:System.Web.UI.HtmlControls.HtmlImage.RenderAttributes(System.Web.UI.HtmlTextWriter)">
          <source>The <ph id="ph1">&lt;xref:System.Web.UI.HtmlControls.HtmlImage.RenderAttributes%2A&gt;</ph> method is used primarily by control developers extending the functionality of the <ph id="ph2">&lt;xref:System.Web.UI.HtmlControls.HtmlImage&gt;</ph> control.</source>
          <target state="translated">Il <ph id="ph1">&lt;xref:System.Web.UI.HtmlControls.HtmlImage.RenderAttributes%2A&gt;</ph> metodo viene usato principalmente dagli sviluppatori di controlli per estendere la funzionalità del <ph id="ph2">&lt;xref:System.Web.UI.HtmlControls.HtmlImage&gt;</ph> controllo.</target>       </trans-unit>
        <trans-unit id="160" translate="yes" xml:space="preserve" extradata="MT" uid="M:System.Web.UI.HtmlControls.HtmlImage.RenderAttributes(System.Web.UI.HtmlTextWriter)">
          <source>The following code example demonstrates how to override the <ph id="ph1">&lt;xref:System.Web.UI.HtmlControls.HtmlImage.RenderAttributes%2A&gt;</ph> method in a custom server control so that specific alternative text, accessible as a ToolTip, is always displayed with the <ph id="ph2">&lt;xref:System.Web.UI.HtmlControls.HtmlImage&gt;</ph> control.</source>
          <target state="translated">Esempio di codice riportato di seguito viene illustrato come eseguire l'override di <ph id="ph1">&lt;xref:System.Web.UI.HtmlControls.HtmlImage.RenderAttributes%2A&gt;</ph> metodo in un server personalizzato controllare in modo specifico testo alternativo, accessibile come descrizione comando, viene visualizzato sempre con il <ph id="ph2">&lt;xref:System.Web.UI.HtmlControls.HtmlImage&gt;</ph> controllo.</target>       </trans-unit>
        <trans-unit id="161" translate="yes" xml:space="preserve" uid="M:System.Web.UI.HtmlControls.HtmlImage.RenderAttributes(System.Web.UI.HtmlTextWriter)">
          <source>The <ph id="ph1">&lt;see cref="P:System.Web.UI.HtmlControls.HtmlImage.Src" /&gt;</ph> property contains a malformed URL.</source>
          <target state="translated">La proprietà <ph id="ph1">&lt;see cref="P:System.Web.UI.HtmlControls.HtmlImage.Src" /&gt;</ph> contiene un URL non valido.</target>       </trans-unit>
        <trans-unit id="162" translate="yes" xml:space="preserve" uid="P:System.Web.UI.HtmlControls.HtmlImage.Src">
          <source>Gets or sets the source of the image file to display.</source>
          <target state="translated">Ottiene o imposta l'origine del file di immagine da visualizzare.</target>       </trans-unit>
        <trans-unit id="163" translate="yes" xml:space="preserve" extradata="MT" uid="P:System.Web.UI.HtmlControls.HtmlImage.Src">
          <source>A string that contains the path to an image file to display.</source>
          <target state="translated">Stringa che contiene il percorso del file di immagine da visualizzare.</target>       </trans-unit>
        <trans-unit id="164" translate="yes" xml:space="preserve" extradata="MT" uid="P:System.Web.UI.HtmlControls.HtmlImage.Src">
          <source>Use this property to specify the path to the image file to display.</source>
          <target state="translated">Utilizzare questa proprietà per specificare il percorso del file di immagine da visualizzare.</target>       </trans-unit>
        <trans-unit id="165" translate="yes" xml:space="preserve" extradata="MT" uid="P:System.Web.UI.HtmlControls.HtmlImage.Src">
          <source>If the image file is in the same directory as the Web page source file that uses it, you can just specify the file name.</source>
          <target state="translated">Se il file di immagine è nella stessa directory del file di origine pagina Web che lo utilizza, è possibile specificare solo il nome del file.</target>       </trans-unit>
        <trans-unit id="166" translate="yes" xml:space="preserve" extradata="MT" uid="P:System.Web.UI.HtmlControls.HtmlImage.Src">
          <source>Otherwise, you must also include the path to the file.</source>
          <target state="translated">In caso contrario, è necessario includere anche il percorso del file.</target>       </trans-unit>
        <trans-unit id="167" translate="yes" xml:space="preserve" extradata="MT" uid="P:System.Web.UI.HtmlControls.HtmlImage.Src">
          <source>The path can be absolute or relative to the directory that contains the Web page source file.</source>
          <target state="translated">Il percorso può essere assoluto o relativo alla directory che contiene il file di origine della pagina Web.</target>       </trans-unit>
        <trans-unit id="168" translate="yes" xml:space="preserve" extradata="MT" uid="P:System.Web.UI.HtmlControls.HtmlImage.Src">
          <source>You can use the relative path " <ph id="ph1">`~/`</ph> " to refer to the current virtual directory where the page is located.</source>
          <target state="translated">È possibile utilizzare il percorso relativo " <ph id="ph1">`~/`</ph> " per fare riferimento alla directory virtuale in cui si trova la pagina corrente.</target>       </trans-unit>
        <trans-unit id="169" translate="yes" xml:space="preserve" extradata="MT" uid="P:System.Web.UI.HtmlControls.HtmlImage.Src">
          <source>For example, the value of <ph id="ph1">&lt;xref:System.Web.UI.HtmlControls.HtmlImage.Src%2A&gt;</ph> for <ph id="ph2">`&lt;img runat="server" src="~/abc/d.gif"&gt;`</ph> on a page in the "XspTest" virtual directory is <ph id="ph3">`&lt;img src="/XspText/abc/d.gif"&gt;`</ph>.</source>
          <target state="translated">Ad esempio, il valore di <ph id="ph1">&lt;xref:System.Web.UI.HtmlControls.HtmlImage.Src%2A&gt;</ph> per <ph id="ph2">`&lt;img runat="server" src="~/abc/d.gif"&gt;`</ph> in una pagina in "XspTest" è la directory virtuale <ph id="ph3">`&lt;img src="/XspText/abc/d.gif"&gt;`</ph>.</target>       </trans-unit>
        <trans-unit id="170" translate="yes" xml:space="preserve" extradata="MT" uid="P:System.Web.UI.HtmlControls.HtmlImage.Src">
          <source>The following code example demonstrates how to use the <ph id="ph1">&lt;xref:System.Web.UI.HtmlControls.HtmlImage.Src%2A&gt;</ph> property to specify an image file to display in the same directory as the Web page source file.</source>
          <target state="translated">Esempio di codice seguente viene illustrato come utilizzare il <ph id="ph1">&lt;xref:System.Web.UI.HtmlControls.HtmlImage.Src%2A&gt;</ph> proprietà per specificare un file di immagine da visualizzare nella stessa directory del file di origine della pagina Web.</target>       </trans-unit>
        <trans-unit id="171" translate="yes" xml:space="preserve" extradata="MT" uid="P:System.Web.UI.HtmlControls.HtmlImage.Src">
          <source>The following code example demonstrates how to use the <ph id="ph1">&lt;xref:System.Web.UI.HtmlControls.HtmlImage.Src%2A&gt;</ph> property to specify an image file to display in a different directory from the Web page source file.</source>
          <target state="translated">Esempio di codice seguente viene illustrato come utilizzare il <ph id="ph1">&lt;xref:System.Web.UI.HtmlControls.HtmlImage.Src%2A&gt;</ph> proprietà per specificare un file di immagine da visualizzare in una directory diversa dal file di origine della pagina Web.</target>       </trans-unit>
        <trans-unit id="172" translate="yes" xml:space="preserve" uid="P:System.Web.UI.HtmlControls.HtmlImage.Width">
          <source>Gets or sets the width of the image.</source>
          <target state="translated">Ottiene o imposta la larghezza dell'immagine.</target>       </trans-unit>
        <trans-unit id="173" translate="yes" xml:space="preserve" extradata="MT" uid="P:System.Web.UI.HtmlControls.HtmlImage.Width">
          <source>The width of the image.</source>
          <target state="translated">Larghezza dell'immagine.</target>       </trans-unit>
        <trans-unit id="174" translate="yes" xml:space="preserve" extradata="MT" uid="P:System.Web.UI.HtmlControls.HtmlImage.Width">
          <source>The <ph id="ph1">&lt;xref:System.Web.UI.HtmlControls.HtmlImage.Height%2A&gt;</ph> and <ph id="ph2">&lt;xref:System.Web.UI.HtmlControls.HtmlImage.Width%2A&gt;</ph> properties can be used two ways.</source>
          <target state="translated">Il <ph id="ph1">&lt;xref:System.Web.UI.HtmlControls.HtmlImage.Height%2A&gt;</ph> e <ph id="ph2">&lt;xref:System.Web.UI.HtmlControls.HtmlImage.Width%2A&gt;</ph> possono essere utilizzate in due modi.</target>       </trans-unit>
        <trans-unit id="175" translate="yes" xml:space="preserve" extradata="MT" uid="P:System.Web.UI.HtmlControls.HtmlImage.Width">
          <source>You can use the <ph id="ph1">&lt;xref:System.Web.UI.HtmlControls.HtmlImage.Height%2A&gt;</ph> and <ph id="ph2">&lt;xref:System.Web.UI.HtmlControls.HtmlImage.Width%2A&gt;</ph> properties to send the image size specifications to the browser.</source>
          <target state="translated">È possibile utilizzare il <ph id="ph1">&lt;xref:System.Web.UI.HtmlControls.HtmlImage.Height%2A&gt;</ph> e <ph id="ph2">&lt;xref:System.Web.UI.HtmlControls.HtmlImage.Width%2A&gt;</ph> le proprietà per inviare l'immagine di specifiche di dimensione per il browser.</target>       </trans-unit>
        <trans-unit id="176" translate="yes" xml:space="preserve" extradata="MT" uid="P:System.Web.UI.HtmlControls.HtmlImage.Width">
          <source>This displays the Web page faster because the browser does not need to recalculate the positions of elements on the page when the image loads.</source>
          <target state="translated">Verrà visualizzata la pagina Web più veloce perché non è necessario ricalcolare le posizioni degli elementi nella pagina quando l'immagine viene caricata nel browser.</target>       </trans-unit>
        <trans-unit id="177" translate="yes" xml:space="preserve" extradata="MT" uid="P:System.Web.UI.HtmlControls.HtmlImage.Width">
          <source>You can also use the <ph id="ph1">&lt;xref:System.Web.UI.HtmlControls.HtmlImage.Height%2A&gt;</ph> and <ph id="ph2">&lt;xref:System.Web.UI.HtmlControls.HtmlImage.Width%2A&gt;</ph> properties to scale the image.</source>
          <target state="translated">È inoltre possibile utilizzare il <ph id="ph1">&lt;xref:System.Web.UI.HtmlControls.HtmlImage.Height%2A&gt;</ph> e <ph id="ph2">&lt;xref:System.Web.UI.HtmlControls.HtmlImage.Width%2A&gt;</ph> proprietà per ridimensionare l'immagine.</target>       </trans-unit>
        <trans-unit id="178" translate="yes" xml:space="preserve" extradata="MT" uid="P:System.Web.UI.HtmlControls.HtmlImage.Width">
          <source>When using values that are different from the physical size of the image, the image is resized accordingly.</source>
          <target state="translated">Quando si utilizzano i valori che sono diversi dalle dimensioni fisiche dell'immagine, l'immagine viene ridimensionata di conseguenza.</target>       </trans-unit>
        <trans-unit id="179" translate="yes" xml:space="preserve" extradata="MT" uid="P:System.Web.UI.HtmlControls.HtmlImage.Width">
          <source>However, this method for scaling the image is not recommended because it takes longer for the page to display it.</source>
          <target state="translated">Tuttavia, questo metodo per il ridimensionamento dell'immagine è sconsigliato, perché richiede più tempo per la visualizzazione della pagina.</target>       </trans-unit>
        <trans-unit id="180" translate="yes" xml:space="preserve" extradata="MT" uid="P:System.Web.UI.HtmlControls.HtmlImage.Width">
          <source>Instead, physically resize the image to the size you need.</source>
          <target state="translated">Consiglia di ridimensionare l'immagine per la dimensione che è necessario.</target>       </trans-unit>
        <trans-unit id="181" translate="yes" xml:space="preserve" extradata="MT" uid="P:System.Web.UI.HtmlControls.HtmlImage.Width">
          <source>By default, the <ph id="ph1">&lt;xref:System.Web.UI.HtmlControls.HtmlImage.Width%2A&gt;</ph> property is expressed in pixels, but it can also be expressed as a percentage of the window size.</source>
          <target state="translated">Per impostazione predefinita, il <ph id="ph1">&lt;xref:System.Web.UI.HtmlControls.HtmlImage.Width%2A&gt;</ph> espresse in pixel, ma può anche essere espressa come percentuale delle dimensioni della finestra.</target>       </trans-unit>
        <trans-unit id="182" translate="yes" xml:space="preserve" extradata="MT" uid="P:System.Web.UI.HtmlControls.HtmlImage.Width">
          <source>The following code example demonstrates how to use the <ph id="ph1">&lt;xref:System.Web.UI.HtmlControls.HtmlImage.Width%2A&gt;</ph> property to programmatically modify the width of the displayed image.</source>
          <target state="translated">Esempio di codice seguente viene illustrato come utilizzare il <ph id="ph1">&lt;xref:System.Web.UI.HtmlControls.HtmlImage.Width%2A&gt;</ph> proprietà per modificare a livello di codice la larghezza dell'immagine visualizzata.</target>       </trans-unit>
      </group>
    </body>
  </file>
</xliff>