<Namespace Name="System.Data.Sql">
  <Metadata>
    <Meta Name="ms.openlocfilehash" Value="4003fc8094689a2b4c08d1661562f6e0c9c72a49" />
    <Meta Name="ms.sourcegitcommit" Value="d0bb31ec8354fa58c62c2a646057eec11d3e2150" />
    <Meta Name="ms.translationtype" Value="HT" />
    <Meta Name="ms.contentlocale" Value="it-IT" />
    <Meta Name="ms.lasthandoff" Value="08/17/2018" />
    <Meta Name="ms.locfileid" Value="30726145" />
  </Metadata>
  <Docs>
    <summary>
      <span data-ttu-id="5c506-101">Lo spazio dei nomi <see cref="N:System.Data.Sql" /> contiene classi che supportano funzionalità specifiche di SQL Server.</span>
      <span class="sxs-lookup">
        <span data-stu-id="5c506-101">The <see cref="N:System.Data.Sql" /> namespace contains classes that support SQL Server-specific functionality.</span>
      </span>
    </summary>
    <remarks>
      <format type="text/markdown"><![CDATA[  
  
## Remarks  
 <span data-ttu-id="5c506-102">Per informazioni sulle funzionalità supportate dalle classi all'interno di questo spazio dei nomi, vedere [enumerazione delle istanze di SQL Server (ADO.NET)](~/docs/framework/data/adonet/sql/enumerating-instances-of-sql-server.md) e [notifiche di Query in SQL Server](~/docs/framework/data/adonet/sql/query-notifications-in-sql-server.md).</span><span class="sxs-lookup"><span data-stu-id="5c506-102">For information about the functionality that the classes within this namespace support, see [Enumerating Instances of SQL Server (ADO.NET)](~/docs/framework/data/adonet/sql/enumerating-instances-of-sql-server.md) and [Query Notifications in SQL Server](~/docs/framework/data/adonet/sql/query-notifications-in-sql-server.md).</span></span>  
  
> [!NOTE]
>  <span data-ttu-id="5c506-103">Nelle versioni beta di ADO.NET versione 2.0, il <xref:System.Data.Sql> dello spazio dei nomi contiene inoltre classi da utilizzare con integrazione in common language runtime (CLR) di SQL Server.</span><span class="sxs-lookup"><span data-stu-id="5c506-103">In beta releases of ADO.NET version 2.0, the <xref:System.Data.Sql> namespace also contained classes for use with SQL Server common language runtime (CLR) integration.</span></span> <span data-ttu-id="5c506-104">Tuttavia, queste classi sono state spostate nel rispettivo spazio dei nomi, <xref:Microsoft.SqlServer.Server>.</span><span class="sxs-lookup"><span data-stu-id="5c506-104">However, those classes have been moved into their own namespace, <xref:Microsoft.SqlServer.Server>.</span></span> <span data-ttu-id="5c506-105">Per altre informazioni sull'utilizzo dell'integrazione CLR di SQL Server, vedere [SQL Server integrazione Common Language Runtime](~/docs/framework/data/adonet/sql/sql-server-common-language-runtime-integration.md).</span><span class="sxs-lookup"><span data-stu-id="5c506-105">For more information about using SQL Server CLR integration, see [SQL Server Common Language Runtime Integration](~/docs/framework/data/adonet/sql/sql-server-common-language-runtime-integration.md).</span></span>  
  
 ]]></format>
    </remarks>
    <altmember cref="N:Microsoft.SqlServer.Server" />
    <altmember cref="N:System.Data.SqlClient" />
  </Docs>
</Namespace>