<?xml version="1.0" encoding="utf-8"?>
<xliff xmlns="urn:oasis:names:tc:xliff:document:1.2" xmlns:xsi="http://www.w3.org/2001/XMLSchema-instance" version="1.2" xsi:schemaLocation="urn:oasis:names:tc:xliff:document:1.2 xliff-core-1.2-transitional.xsd">
  <file datatype="xml" original="XpsDigitalSignature.xml" source-language="en-US" target-language="it-IT">
    <header>
      <tool tool-id="mdxliff" tool-name="mdxliff" tool-version="1.0-efd8310" tool-company="Microsoft" />
      <xliffext:skl_file_name xmlns:xliffext="urn:microsoft:content:schema:xliffextensions">b891ec5d-4b60-42d7-ac21-95eab9e3ef826d1770535e6a033e6e64b337a551feafdef8f7ac.skl</xliffext:skl_file_name>
      <xliffext:version xmlns:xliffext="urn:microsoft:content:schema:xliffextensions">1.2</xliffext:version>
      <xliffext:ms.openlocfilehash xmlns:xliffext="urn:microsoft:content:schema:xliffextensions">6d1770535e6a033e6e64b337a551feafdef8f7ac</xliffext:ms.openlocfilehash>
      <xliffext:ms.sourcegitcommit xmlns:xliffext="urn:microsoft:content:schema:xliffextensions">058bfa0b75b777d3171411d35da8f11617fc06b0</xliffext:ms.sourcegitcommit>
      <xliffext:ms.lasthandoff xmlns:xliffext="urn:microsoft:content:schema:xliffextensions">05/04/2018</xliffext:ms.lasthandoff>
      <xliffext:moniker_ids xmlns:xliffext="urn:microsoft:content:schema:xliffextensions">netframework-4.5.1,netframework-4.5.2,netframework-4.5,netframework-4.6.1,netframework-4.6.2,netframework-4.6,netframework-4.7.1,netframework-4.7.2,netframework-4.7</xliffext:moniker_ids>
    </header>
    <body>
      <group id="content" extype="content">
        <trans-unit id="101" translate="yes" xml:space="preserve" uid="T:System.Windows.Xps.Packaging.XpsDigitalSignature">
          <source>Represents a digital signature for an <ph id="ph1">&lt;see cref="T:System.Windows.Xps.Packaging.XpsDocument" /&gt;</ph>.</source>
          <target state="translated">Rappresenta una firma digitale per un <ph id="ph1">&lt;see cref="T:System.Windows.Xps.Packaging.XpsDocument" /&gt;</ph>.</target>       </trans-unit>
        <trans-unit id="102" translate="yes" xml:space="preserve" extradata="MT" uid="T:System.Windows.Xps.Packaging.XpsDigitalSignature">
          <source>Use <ph id="ph1">&lt;xref:System.Windows.Xps.Packaging.XpsDigitalSignature&gt;</ph> instead of <ph id="ph2">&lt;xref:System.IO.Packaging.PackageDigitalSignature&gt;</ph> when you work with an <ph id="ph3">[!INCLUDE[TLA2#tla_xps](~/includes/tla2sharptla-xps-md.md)]</ph> document.</source>
          <target state="translated">Utilizzare <ph id="ph1">&lt;xref:System.Windows.Xps.Packaging.XpsDigitalSignature&gt;</ph> anziché <ph id="ph2">&lt;xref:System.IO.Packaging.PackageDigitalSignature&gt;</ph> quando si lavora con un <ph id="ph3">[!INCLUDE[TLA2#tla_xps](~/includes/tla2sharptla-xps-md.md)]</ph> documento.</target>       </trans-unit>
        <trans-unit id="103" translate="yes" xml:space="preserve" extradata="MT" uid="T:System.Windows.Xps.Packaging.XpsDigitalSignature">
          <source><ph id="ph1">&lt;xref:System.IO.Packaging.PackageDigitalSignature&gt;</ph> is not <ph id="ph2">[!INCLUDE[TLA2#tla_xps](~/includes/tla2sharptla-xps-md.md)]</ph>-aware, and does not guarantee that all parts in an <ph id="ph3">[!INCLUDE[TLA2#tla_xps](~/includes/tla2sharptla-xps-md.md)]</ph> document are fully signed.</source>
          <target state="translated"><ph id="ph1">&lt;xref:System.IO.Packaging.PackageDigitalSignature&gt;</ph> non è <ph id="ph2">[!INCLUDE[TLA2#tla_xps](~/includes/tla2sharptla-xps-md.md)]</ph>-compatibile con e non garantisce che tutte le parti un <ph id="ph3">[!INCLUDE[TLA2#tla_xps](~/includes/tla2sharptla-xps-md.md)]</ph> documento sono completamente firmati.</target>       </trans-unit>
        <trans-unit id="104" translate="yes" xml:space="preserve" extradata="MT" uid="T:System.Windows.Xps.Packaging.XpsDigitalSignature">
          <source>For more information about digital signatures, see the MSDN article <bpt id="p1">*</bpt>Digital Signing Framework of the Open Packaging Conventions<ept id="p1">*</ept> available at <bpt id="p2">[</bpt><ph id="ph1">http://go.microsoft.com/fwlink/?LinkId=74494</ph><ept id="p2">](http://go.microsoft.com/fwlink/?LinkId=74494)</ept>.</source>
          <target state="translated">Per ulteriori informazioni sulle firme digitali, vedere l'articolo MSDN <bpt id="p1">*</bpt>Framework di Open Packaging Conventions firma digitale<ept id="p1">*</ept> disponibile all'indirizzo <bpt id="p2">[</bpt> <ph id="ph1">http://go.microsoft.com/fwlink/?LinkId=74494</ph> <ept id="p2">](http://go.microsoft.com/fwlink/?LinkId=74494)</ept>.</target>       </trans-unit>
        <trans-unit id="105" translate="yes" xml:space="preserve" extradata="MT" uid="T:System.Windows.Xps.Packaging.XpsDigitalSignature">
          <source>For more information about <ph id="ph1">[!INCLUDE[TLA2#tla_xps](~/includes/tla2sharptla-xps-md.md)]</ph> see the <bpt id="p1">*</bpt>XML Paper Specification (XPS)<ept id="p1">*</ept> available for download at <bpt id="p2">[</bpt><ph id="ph2">http://go.microsoft.com/fwlink/?LinkID=65761</ph><ept id="p2">](http://go.microsoft.com/fwlink/?LinkID=65761)</ept>.</source>
          <target state="translated">Per ulteriori informazioni <ph id="ph1">[!INCLUDE[TLA2#tla_xps](~/includes/tla2sharptla-xps-md.md)]</ph> vedere il <bpt id="p1">*</bpt>XML Paper Specification (XPS)<ept id="p1">*</ept> disponibili per il download all'indirizzo <bpt id="p2">[</bpt> <ph id="ph2">http://go.microsoft.com/fwlink/?LinkID=65761</ph> <ept id="p2">](http://go.microsoft.com/fwlink/?LinkID=65761)</ept>.</target>       </trans-unit>
        <trans-unit id="106" translate="yes" xml:space="preserve" uid="M:System.Windows.Xps.Packaging.XpsDigitalSignature.#ctor(System.IO.Packaging.PackageDigitalSignature,System.Windows.Xps.Packaging.XpsDocument)">
          <source>The associated digital signature for the package.</source>
          <target state="translated">Firma digitale associata per il pacchetto.</target>       </trans-unit>
        <trans-unit id="107" translate="yes" xml:space="preserve" uid="M:System.Windows.Xps.Packaging.XpsDigitalSignature.#ctor(System.IO.Packaging.PackageDigitalSignature,System.Windows.Xps.Packaging.XpsDocument)">
          <source>The associated package.</source>
          <target state="translated">Pacchetto associato.</target>       </trans-unit>
        <trans-unit id="108" translate="yes" xml:space="preserve" uid="M:System.Windows.Xps.Packaging.XpsDigitalSignature.#ctor(System.IO.Packaging.PackageDigitalSignature,System.Windows.Xps.Packaging.XpsDocument)">
          <source>Initializes a new instance of the <ph id="ph1">&lt;see cref="T:System.Windows.Xps.Packaging.XpsDigitalSignature" /&gt;</ph> class.</source>
          <target state="translated">Inizializza una nuova istanza della classe <ph id="ph1">&lt;see cref="T:System.Windows.Xps.Packaging.XpsDigitalSignature" /&gt;</ph>.</target>       </trans-unit>
        <trans-unit id="109" translate="yes" xml:space="preserve" uid="P:System.Windows.Xps.Packaging.XpsDigitalSignature.DocumentPropertiesRestricted">
          <source>Gets a value that indicates whether changing the properties of the document invalidates the digital signature.</source>
          <target state="translated">Ottiene un valore che indica se la modifica delle proprietà del documento invalida la firma digitale.</target>       </trans-unit>
        <trans-unit id="110" translate="yes" xml:space="preserve" extradata="MT" uid="P:System.Windows.Xps.Packaging.XpsDigitalSignature.DocumentPropertiesRestricted">
          <source><ph id="ph1">&lt;see langword="true" /&gt;</ph> if changing the properties of the document invalidates the signature; otherwise, <ph id="ph2">&lt;see langword="false" /&gt;</ph>.</source>
          <target state="translated"><ph id="ph1">&lt;see langword="true" /&gt;</ph> se la modifica delle proprietà del documento invalida la firma; in caso contrario, <ph id="ph2">&lt;see langword="false" /&gt;</ph>.</target>       </trans-unit>
        <trans-unit id="111" translate="yes" xml:space="preserve" uid="P:System.Windows.Xps.Packaging.XpsDigitalSignature.Id">
          <source>Gets the globally unique identifier (GUID) of the signature.</source>
          <target state="translated">Ottiene l'identificatore univoco globale (GUID) della firma.</target>       </trans-unit>
        <trans-unit id="112" translate="yes" xml:space="preserve" extradata="MT" uid="P:System.Windows.Xps.Packaging.XpsDigitalSignature.Id">
          <source>The GUID of the signature.</source>
          <target state="translated">Il GUID della firma.</target>       </trans-unit>
        <trans-unit id="113" translate="yes" xml:space="preserve" extradata="MT" uid="P:System.Windows.Xps.Packaging.XpsDigitalSignature.Id">
          <source>The following example shows how to use the <ph id="ph1">&lt;xref:System.Windows.Xps.Packaging.XpsDigitalSignature.Id%2A&gt;</ph> property to display and update signature information.</source>
          <target state="translated">Nell'esempio seguente viene illustrato come utilizzare il <ph id="ph1">&lt;xref:System.Windows.Xps.Packaging.XpsDigitalSignature.Id%2A&gt;</ph> proprietà per visualizzare e aggiornare le informazioni sulla firma.</target>       </trans-unit>
        <trans-unit id="114" translate="yes" xml:space="preserve" uid="P:System.Windows.Xps.Packaging.XpsDigitalSignature.IsCertificateAvailable">
          <source>Gets a value that indicates whether the signer's X.509 certificate is contained in the document <ph id="ph1">&lt;see cref="T:System.IO.Packaging.Package" /&gt;</ph>.</source>
          <target state="translated">Ottiene un valore che indica se il certificato X.509 del firmatario è contenuto nell'oggetto <ph id="ph1">&lt;see cref="T:System.IO.Packaging.Package" /&gt;</ph> del documento.</target>       </trans-unit>
        <trans-unit id="115" translate="yes" xml:space="preserve" extradata="MT" uid="P:System.Windows.Xps.Packaging.XpsDigitalSignature.IsCertificateAvailable">
          <source><ph id="ph1">&lt;see langword="true" /&gt;</ph> if the X.509 certificate of the signer is embedded in the document <ph id="ph2">&lt;see cref="T:System.IO.Packaging.Package" /&gt;</ph>; otherwise, <ph id="ph3">&lt;see langword="false" /&gt;</ph>.</source>
          <target state="translated"><ph id="ph1">&lt;see langword="true" /&gt;</ph> Se il certificato x. 509 del firmatario è incorporato nel documento <ph id="ph2">&lt;see cref="T:System.IO.Packaging.Package" /&gt;</ph>; in caso contrario, <ph id="ph3">&lt;see langword="false" /&gt;</ph>.</target>       </trans-unit>
        <trans-unit id="116" translate="yes" xml:space="preserve" extradata="MT" uid="P:System.Windows.Xps.Packaging.XpsDigitalSignature.IsCertificateAvailable">
          <source>The X.509 certificate of the signer is embedded by the <ph id="ph1">&lt;xref:System.Windows.Xps.Packaging.XpsDocument.SignDigitally%2A&gt;</ph> method when called with the <ph id="ph2">`embedCertificate`</ph> parameter set to <ph id="ph3">`true`</ph>.</source>
          <target state="translated">Il certificato x. 509 del firmatario è incorporato per il <ph id="ph1">&lt;xref:System.Windows.Xps.Packaging.XpsDocument.SignDigitally%2A&gt;</ph> metodo quando viene chiamato con il <ph id="ph2">`embedCertificate`</ph> parametro impostato su <ph id="ph3">`true`</ph>.</target>       </trans-unit>
        <trans-unit id="117" translate="yes" xml:space="preserve" extradata="MT" uid="P:System.Windows.Xps.Packaging.XpsDigitalSignature.IsCertificateAvailable">
          <source>For more information on digital signatures and certificates, see Section 3.3 Digital Signatures in the <bpt id="p1">*</bpt>Open Packaging Conventions<ept id="p1">*</ept> specification available for download at <bpt id="p2">[</bpt><ph id="ph1">http://go.microsoft.com/fwlink/?LinkID=71255</ph><ept id="p2">](http://go.microsoft.com/fwlink/?LinkID=71255)</ept>.</source>
          <target state="translated">Per ulteriori informazioni su firme digitali e certificati, vedere la sezione 3.3 firme digitali nel <bpt id="p1">*</bpt>Open Packaging Conventions<ept id="p1">*</ept> specifica disponibile per il download all'indirizzo <bpt id="p2">[</bpt> <ph id="ph1">http://go.microsoft.com/fwlink/?LinkID=71255</ph> <ept id="p2">](http://go.microsoft.com/fwlink/?LinkID=71255)</ept>.</target>       </trans-unit>
        <trans-unit id="118" translate="yes" xml:space="preserve" uid="P:System.Windows.Xps.Packaging.XpsDigitalSignature.SignatureOriginRestricted">
          <source>Gets a value that indicates whether the digital signature is invalidated if someone else signs the package.</source>
          <target state="translated">Ottiene un valore che indica se la firma digitale viene invalidata in caso di firma del package da parte di altri.</target>       </trans-unit>
        <trans-unit id="119" translate="yes" xml:space="preserve" extradata="MT" uid="P:System.Windows.Xps.Packaging.XpsDigitalSignature.SignatureOriginRestricted">
          <source><ph id="ph1">&lt;see langword="true" /&gt;</ph> if the signature is invalidated if an additional digital signature is applied; otherwise, <ph id="ph2">&lt;see langword="false" /&gt;</ph>.</source>
          <target state="translated"><ph id="ph1">&lt;see langword="true" /&gt;</ph> se la firma viene invalidata in caso di applicazione di una firma digitale aggiuntiva; in caso contrario, <ph id="ph2">&lt;see langword="false" /&gt;</ph>.</target>       </trans-unit>
        <trans-unit id="120" translate="yes" xml:space="preserve" extradata="MT" uid="P:System.Windows.Xps.Packaging.XpsDigitalSignature.SignatureOriginRestricted">
          <source>The signature origin restriction is set by the <ph id="ph1">&lt;xref:System.Windows.Xps.Packaging.XpsDocument.SignDigitally%2A&gt;</ph> method when called with the <ph id="ph2">`restrictions`</ph> parameter set to exclude the <ph id="ph3">&lt;xref:System.Windows.Xps.Packaging.XpsDigSigPartAlteringRestrictions.SignatureOrigin&gt;</ph> part.</source>
          <target state="translated">La restrizione di origine della firma è l'impostazione di <ph id="ph1">&lt;xref:System.Windows.Xps.Packaging.XpsDocument.SignDigitally%2A&gt;</ph> metodo quando viene chiamato con il <ph id="ph2">`restrictions`</ph> parametro impostato per escludere il <ph id="ph3">&lt;xref:System.Windows.Xps.Packaging.XpsDigSigPartAlteringRestrictions.SignatureOrigin&gt;</ph> parte.</target>       </trans-unit>
        <trans-unit id="121" translate="yes" xml:space="preserve" extradata="MT" uid="P:System.Windows.Xps.Packaging.XpsDigitalSignature.SignatureOriginRestricted">
          <source>If a document is to be signed by more than one person, the <ph id="ph1">&lt;xref:System.Windows.Xps.Packaging.XpsDigSigPartAlteringRestrictions.SignatureOrigin&gt;</ph> part needs to be excluded from the signature when the document is first signed.</source>
          <target state="translated">Se un documento deve essere firmato da più di una persona, di <ph id="ph1">&lt;xref:System.Windows.Xps.Packaging.XpsDigSigPartAlteringRestrictions.SignatureOrigin&gt;</ph> parte deve essere esclusa dalla firma quando il documento è già firmato.</target>       </trans-unit>
        <trans-unit id="122" translate="yes" xml:space="preserve" extradata="MT" uid="P:System.Windows.Xps.Packaging.XpsDigitalSignature.SignatureOriginRestricted">
          <source>(Exclusions are specified in the <ph id="ph1">`restrictions`</ph> parameter of the call to <ph id="ph2">&lt;xref:System.Windows.Xps.Packaging.XpsDocument.SignDigitally%2A&gt;</ph>.)  If the <ph id="ph3">&lt;xref:System.Windows.Xps.Packaging.XpsDigSigPartAlteringRestrictions.SignatureOrigin&gt;</ph> part is not excluded, any additional signatures invalidate the signature of the first signer.</source>
          <target state="translated">(Esclusioni sono specificate nel <ph id="ph1">`restrictions`</ph> parametro della chiamata a <ph id="ph2">&lt;xref:System.Windows.Xps.Packaging.XpsDocument.SignDigitally%2A&gt;</ph>.)  Se il <ph id="ph3">&lt;xref:System.Windows.Xps.Packaging.XpsDigSigPartAlteringRestrictions.SignatureOrigin&gt;</ph> parte non viene escluso, le eventuali firme aggiuntive invalidano la firma del primo firmatario.</target>       </trans-unit>
        <trans-unit id="123" translate="yes" xml:space="preserve" extradata="MT" uid="P:System.Windows.Xps.Packaging.XpsDigitalSignature.SignatureOriginRestricted">
          <source>For more information on the Core Properties and Signature Origin parts, see Chapter 3 of the <bpt id="p1">*</bpt>Open Packaging Conventions<ept id="p1">*</ept> specification available for download at <bpt id="p2">[</bpt><ph id="ph1">http://go.microsoft.com/fwlink/?LinkID=71255</ph><ept id="p2">](http://go.microsoft.com/fwlink/?LinkID=71255)</ept>.</source>
          <target state="translated">Per ulteriori informazioni sulle proprietà dei componenti di base e le parti dell'origine di firma, vedere il capitolo 3 del <bpt id="p1">*</bpt>Open Packaging Conventions<ept id="p1">*</ept> specifica disponibile per il download all'indirizzo <bpt id="p2">[</bpt> <ph id="ph1">http://go.microsoft.com/fwlink/?LinkID=71255</ph> <ept id="p2">](http://go.microsoft.com/fwlink/?LinkID=71255)</ept>.</target>       </trans-unit>
        <trans-unit id="124" translate="yes" xml:space="preserve" uid="P:System.Windows.Xps.Packaging.XpsDigitalSignature.SignatureType">
          <source>Gets a <ph id="ph1">[!INCLUDE[TLA2#tla_url](~/includes/tla2sharptla-url-md.md)]</ph> string that identifies the signature type.</source>
          <target state="translated">Ottiene una stringa <ph id="ph1">[!INCLUDE[TLA2#tla_url](~/includes/tla2sharptla-url-md.md)]</ph> che identifica il tipo di firma.</target>       </trans-unit>
        <trans-unit id="125" translate="yes" xml:space="preserve" extradata="MT" uid="P:System.Windows.Xps.Packaging.XpsDigitalSignature.SignatureType">
          <source>A <ph id="ph1">[!INCLUDE[TLA2#tla_url](~/includes/tla2sharptla-url-md.md)]</ph> string that identifies the signature type.</source>
          <target state="translated">Stringa <ph id="ph1">[!INCLUDE[TLA2#tla_url](~/includes/tla2sharptla-url-md.md)]</ph> che identifica il tipo di firma.</target>       </trans-unit>
        <trans-unit id="126" translate="yes" xml:space="preserve" extradata="MT" uid="P:System.Windows.Xps.Packaging.XpsDigitalSignature.SignatureType">
          <source>The default signature type is <ph id="ph1">&lt;see cref="F:System.Security.Cryptography.Xml.SignedXml.XmlDsigC14NTransformUrl" /&gt;</ph>.</source>
          <target state="translated">Il tipo di firma predefinito è <ph id="ph1">&lt;see cref="F:System.Security.Cryptography.Xml.SignedXml.XmlDsigC14NTransformUrl" /&gt;</ph>.</target>       </trans-unit>
        <trans-unit id="127" translate="yes" xml:space="preserve" uid="P:System.Windows.Xps.Packaging.XpsDigitalSignature.SignatureValue">
          <source>Gets the encrypted hash value of the signature.</source>
          <target state="translated">Ottiene il valore hash crittografato della firma.</target>       </trans-unit>
        <trans-unit id="128" translate="yes" xml:space="preserve" extradata="MT" uid="P:System.Windows.Xps.Packaging.XpsDigitalSignature.SignatureValue">
          <source>A <ph id="ph1">&lt;see cref="T:System.Byte" /&gt;</ph> array that contains the encrypted hash value of the signature.</source>
          <target state="translated">Matrice <ph id="ph1">&lt;see cref="T:System.Byte" /&gt;</ph> che contiene il valore hash crittografato della firma.</target>       </trans-unit>
        <trans-unit id="129" translate="yes" xml:space="preserve" uid="P:System.Windows.Xps.Packaging.XpsDigitalSignature.SignedDocumentSequence">
          <source>Gets the document sequence reader for the signed document sequence.</source>
          <target state="translated">Ottiene il lettore di sequenza di documenti per la sequenza di documenti firmati.</target>       </trans-unit>
        <trans-unit id="130" translate="yes" xml:space="preserve" extradata="MT" uid="P:System.Windows.Xps.Packaging.XpsDigitalSignature.SignedDocumentSequence">
          <source>An <ph id="ph1">&lt;see cref="T:System.Windows.Xps.Packaging.IXpsFixedDocumentSequenceReader" /&gt;</ph>; or <ph id="ph2">&lt;see langword="null" /&gt;</ph> if not all valid <ph id="ph3">[!INCLUDE[TLA2#tla_xps](~/includes/tla2sharptla-xps-md.md)]</ph> parts have been signed in the document.</source>
          <target state="translated">Un <ph id="ph1">&lt;see cref="T:System.Windows.Xps.Packaging.IXpsFixedDocumentSequenceReader" /&gt;</ph>; o <ph id="ph2">&lt;see langword="null" /&gt;</ph> se non tutti validi <ph id="ph3">[!INCLUDE[TLA2#tla_xps](~/includes/tla2sharptla-xps-md.md)]</ph> firmate parti del documento.</target>       </trans-unit>
        <trans-unit id="131" translate="yes" xml:space="preserve" uid="P:System.Windows.Xps.Packaging.XpsDigitalSignature.SignerCertificate">
          <source>Gets the X.509 certificate of the signer.</source>
          <target state="translated">Ottiene il certificato X.509 del firmatario.</target>       </trans-unit>
        <trans-unit id="132" translate="yes" xml:space="preserve" extradata="MT" uid="P:System.Windows.Xps.Packaging.XpsDigitalSignature.SignerCertificate">
          <source>The X.509 certificate of the signer; or <ph id="ph1">&lt;see langword="null" /&gt;</ph> when there is no certificate embedded in the document package.</source>
          <target state="translated">Il certificato x. 509 del firmatario. o <ph id="ph1">&lt;see langword="null" /&gt;</ph> quando nessun certificato è incorporato nel pacchetto del documento.</target>       </trans-unit>
        <trans-unit id="133" translate="yes" xml:space="preserve" extradata="MT" uid="P:System.Windows.Xps.Packaging.XpsDigitalSignature.SignerCertificate">
          <source>The X.509 certificate of the signer is embedded by the <ph id="ph1">&lt;xref:System.Windows.Xps.Packaging.XpsDocument.SignDigitally%2A&gt;</ph> method when called with the <ph id="ph2">`embedCertificate`</ph> parameter set to <ph id="ph3">`true`</ph>.</source>
          <target state="translated">Il certificato x. 509 del firmatario è incorporato per il <ph id="ph1">&lt;xref:System.Windows.Xps.Packaging.XpsDocument.SignDigitally%2A&gt;</ph> metodo quando viene chiamato con il <ph id="ph2">`embedCertificate`</ph> parametro impostato su <ph id="ph3">`true`</ph>.</target>       </trans-unit>
        <trans-unit id="134" translate="yes" xml:space="preserve" extradata="MT" uid="P:System.Windows.Xps.Packaging.XpsDigitalSignature.SignerCertificate">
          <source>For more information on digital signatures and certificates, see Section 3.3 Digital Signatures in the <bpt id="p1">*</bpt>Open Packaging Conventions<ept id="p1">*</ept> specification available for download at <bpt id="p2">[</bpt><ph id="ph1">http://go.microsoft.com/fwlink/?LinkID=71255</ph><ept id="p2">](http://go.microsoft.com/fwlink/?LinkID=71255)</ept>.</source>
          <target state="translated">Per ulteriori informazioni su firme digitali e certificati, vedere la sezione 3.3 firme digitali nel <bpt id="p1">*</bpt>Open Packaging Conventions<ept id="p1">*</ept> specifica disponibile per il download all'indirizzo <bpt id="p2">[</bpt> <ph id="ph1">http://go.microsoft.com/fwlink/?LinkID=71255</ph> <ept id="p2">](http://go.microsoft.com/fwlink/?LinkID=71255)</ept>.</target>       </trans-unit>
        <trans-unit id="135" translate="yes" xml:space="preserve" uid="P:System.Windows.Xps.Packaging.XpsDigitalSignature.SigningTime">
          <source>Gets the date and time when the signature was created.</source>
          <target state="translated">Ottiene la data e l'ora di creazione della firma.</target>       </trans-unit>
        <trans-unit id="136" translate="yes" xml:space="preserve" extradata="MT" uid="P:System.Windows.Xps.Packaging.XpsDigitalSignature.SigningTime">
          <source>The date and time when the pages, document, or document sequence was signed.</source>
          <target state="translated">Data e ora quando le pagine, il documento o la sequenza di documenti è stata firmata.</target>       </trans-unit>
        <trans-unit id="137" translate="yes" xml:space="preserve" extradata="MT" uid="P:System.Windows.Xps.Packaging.XpsDigitalSignature.SigningTime">
          <source><ph id="ph1">&lt;xref:System.Windows.Xps.Packaging.XpsDigitalSignature.SigningTime%2A&gt;</ph> is based on the system time of the computer where the signing took place.</source>
          <target state="translated"><ph id="ph1">&lt;xref:System.Windows.Xps.Packaging.XpsDigitalSignature.SigningTime%2A&gt;</ph> si basa sull'ora di sistema del computer in cui è stata apposta la firma.</target>       </trans-unit>
        <trans-unit id="138" translate="yes" xml:space="preserve" extradata="MT" uid="P:System.Windows.Xps.Packaging.XpsDigitalSignature.SigningTime">
          <source><ph id="ph1">&lt;xref:System.Windows.Xps.Packaging.XpsDigitalSignature.SigningTime%2A&gt;</ph> is not a "secure Time Stamp" and is not from trusted Time Stamp Authority.</source>
          <target state="translated"><ph id="ph1">&lt;xref:System.Windows.Xps.Packaging.XpsDigitalSignature.SigningTime%2A&gt;</ph> non è un "Timestamp sicuro" e non dall'indicatore di data e un'autorità attendibile.</target>       </trans-unit>
        <trans-unit id="139" translate="yes" xml:space="preserve" extradata="MT" uid="P:System.Windows.Xps.Packaging.XpsDigitalSignature.SigningTime">
          <source>A secure TimeStamp must be obtained and applied through a trusted Time Stamp Authority.</source>
          <target state="translated">Un TimeStamp sicuro deve essere ottenuto e applicato tramite un'autorità attendibile di indicatore di data e ora.</target>       </trans-unit>
        <trans-unit id="140" translate="yes" xml:space="preserve" uid="T:System.Windows.Xps.Packaging.XpsDigitalSignature">
          <source>Verifies the document digital signature against an X.509 certificate.</source>
          <target state="translated">Verifica la firma digitale del documento in base a un certificato X.509.</target>       </trans-unit>
        <trans-unit id="141" translate="yes" xml:space="preserve" uid="M:System.Windows.Xps.Packaging.XpsDigitalSignature.Verify">
          <source>Verifies the document digital signature against the X.509 certificate embedded in the <ph id="ph1">[!INCLUDE[TLA2#tla_xps](~/includes/tla2sharptla-xps-md.md)]</ph> <ph id="ph2">&lt;see cref="T:System.IO.Packaging.Package" /&gt;</ph>.</source>
          <target state="translated">Verifica la firma digitale del documento rispetto al certificato X.509 incorporato nell'oggetto <ph id="ph2">&lt;see cref="T:System.IO.Packaging.Package" /&gt;</ph> <ph id="ph1">[!INCLUDE[TLA2#tla_xps](~/includes/tla2sharptla-xps-md.md)]</ph>.</target>       </trans-unit>
        <trans-unit id="142" translate="yes" xml:space="preserve" uid="M:System.Windows.Xps.Packaging.XpsDigitalSignature.Verify">
          <source>One of the <ph id="ph1">&lt;see cref="T:System.IO.Packaging.VerifyResult" /&gt;</ph> enumeration values that specify the result of the verification attempt.</source>
          <target state="translated">Uno dei valori di enumerazione <ph id="ph1">&lt;see cref="T:System.IO.Packaging.VerifyResult" /&gt;</ph> che specificano il risultato del tentativo della verifica.</target>       </trans-unit>
        <trans-unit id="143" translate="yes" xml:space="preserve" extradata="MT" uid="M:System.Windows.Xps.Packaging.XpsDigitalSignature.Verify">
          <source>This overload method verifies the document digital signature against the X.509 certificate embedded by the <ph id="ph1">&lt;xref:System.Windows.Xps.Packaging.XpsDocument.SignDigitally%2A&gt;</ph> method when called with the <ph id="ph2">`embedCertificate`</ph> parameter set to <ph id="ph3">`true`</ph>.</source>
          <target state="translated">Questo metodo di overload verifica la firma digitale del documento rispetto al certificato x. 509 incorporato per il <ph id="ph1">&lt;xref:System.Windows.Xps.Packaging.XpsDocument.SignDigitally%2A&gt;</ph> metodo quando viene chiamato con il <ph id="ph2">`embedCertificate`</ph> parametro impostato su <ph id="ph3">`true`</ph>.</target>       </trans-unit>
        <trans-unit id="144" translate="yes" xml:space="preserve" uid="M:System.Windows.Xps.Packaging.XpsDigitalSignature.Verify(System.Security.Cryptography.X509Certificates.X509Certificate)">
          <source>The certificate of authenticity for the signer.</source>
          <target state="translated">Certificato di autenticità del firmatario.</target>       </trans-unit>
        <trans-unit id="145" translate="yes" xml:space="preserve" uid="M:System.Windows.Xps.Packaging.XpsDigitalSignature.Verify(System.Security.Cryptography.X509Certificates.X509Certificate)">
          <source>Verifies the document digital signature against a specified X.509 certificate.</source>
          <target state="translated">Verifica la firma digitale del documento in base a un certificato X.509 specificato.</target>       </trans-unit>
        <trans-unit id="146" translate="yes" xml:space="preserve" uid="M:System.Windows.Xps.Packaging.XpsDigitalSignature.Verify(System.Security.Cryptography.X509Certificates.X509Certificate)">
          <source>One of the <ph id="ph1">&lt;see cref="T:System.IO.Packaging.VerifyResult" /&gt;</ph> enumeration values that specify the result of the verification attempt.</source>
          <target state="translated">Uno dei valori di enumerazione <ph id="ph1">&lt;see cref="T:System.IO.Packaging.VerifyResult" /&gt;</ph> che specificano il risultato del tentativo della verifica.</target>       </trans-unit>
        <trans-unit id="147" translate="yes" xml:space="preserve" uid="T:System.Windows.Xps.Packaging.XpsDigitalSignature">
          <source>Verifies an X.509 certificate.</source>
          <target state="translated">Verifica un certificato X.509.</target>       </trans-unit>
        <trans-unit id="148" translate="yes" xml:space="preserve" uid="M:System.Windows.Xps.Packaging.XpsDigitalSignature.VerifyCertificate">
          <source>Verifies the X.509 certificate embedded in the package.</source>
          <target state="translated">Verifica il certificato X.509 incorporato nel pacchetto.</target>       </trans-unit>
        <trans-unit id="149" translate="yes" xml:space="preserve" uid="M:System.Windows.Xps.Packaging.XpsDigitalSignature.VerifyCertificate">
          <source>A bitwise combination of the enumeration values that specify the result of the verification attempt.</source>
          <target state="translated">Combinazione bit per bit dei valori di enumerazione che specificano il risultato del tentativo di verifica.</target>       </trans-unit>
        <trans-unit id="150" translate="yes" xml:space="preserve" extradata="MT" uid="M:System.Windows.Xps.Packaging.XpsDigitalSignature.VerifyCertificate">
          <source>Your application will need to decide what flags are critical for verifying certificates.</source>
          <target state="translated">L'applicazione sarà necessario decidere quali flag sono fondamentali per la verifica dei certificati.</target>       </trans-unit>
        <trans-unit id="151" translate="yes" xml:space="preserve" extradata="MT" uid="M:System.Windows.Xps.Packaging.XpsDigitalSignature.VerifyCertificate">
          <source>Some certificate verifications may require Internet connectivity.</source>
          <target state="translated">Alcune verifiche del certificato potrebbero richiedere la connessione a Internet.</target>       </trans-unit>
        <trans-unit id="152" translate="yes" xml:space="preserve" extradata="MT" uid="M:System.Windows.Xps.Packaging.XpsDigitalSignature.VerifyCertificate">
          <source>The X.509 certificate of the signer is embedded by the <ph id="ph1">&lt;xref:System.Windows.Xps.Packaging.XpsDocument.SignDigitally%2A&gt;</ph> method when called with the <ph id="ph2">`embedCertificate`</ph> parameter set to <ph id="ph3">`true`</ph>.</source>
          <target state="translated">Il certificato x. 509 del firmatario è incorporato per il <ph id="ph1">&lt;xref:System.Windows.Xps.Packaging.XpsDocument.SignDigitally%2A&gt;</ph> metodo quando viene chiamato con il <ph id="ph2">`embedCertificate`</ph> parametro impostato su <ph id="ph3">`true`</ph>.</target>       </trans-unit>
        <trans-unit id="153" translate="yes" xml:space="preserve" uid="M:System.Windows.Xps.Packaging.XpsDigitalSignature.VerifyCertificate(System.Security.Cryptography.X509Certificates.X509Certificate)">
          <source>A certificate of authenticity.</source>
          <target state="translated">Certificato di autenticità.</target>       </trans-unit>
        <trans-unit id="154" translate="yes" xml:space="preserve" uid="M:System.Windows.Xps.Packaging.XpsDigitalSignature.VerifyCertificate(System.Security.Cryptography.X509Certificates.X509Certificate)">
          <source>Verifies the specified X.509 certificate.</source>
          <target state="translated">Verifica il certificato X.509 specificato.</target>       </trans-unit>
        <trans-unit id="155" translate="yes" xml:space="preserve" uid="M:System.Windows.Xps.Packaging.XpsDigitalSignature.VerifyCertificate(System.Security.Cryptography.X509Certificates.X509Certificate)">
          <source>A bitwise combination of the enumeration values that specify the result of the verification attempt.</source>
          <target state="translated">Combinazione bit per bit dei valori di enumerazione che specificano il risultato del tentativo di verifica.</target>       </trans-unit>
        <trans-unit id="156" translate="yes" xml:space="preserve" extradata="MT" uid="M:System.Windows.Xps.Packaging.XpsDigitalSignature.VerifyCertificate(System.Security.Cryptography.X509Certificates.X509Certificate)">
          <source>Your application will need to decide what flags are critical for verifying certificates.</source>
          <target state="translated">L'applicazione sarà necessario decidere quali flag sono fondamentali per la verifica dei certificati.</target>       </trans-unit>
        <trans-unit id="157" translate="yes" xml:space="preserve" extradata="MT" uid="M:System.Windows.Xps.Packaging.XpsDigitalSignature.VerifyCertificate(System.Security.Cryptography.X509Certificates.X509Certificate)">
          <source>Some certificate verifications may require Internet connectivity.</source>
          <target state="translated">Alcune verifiche del certificato potrebbero richiedere la connessione a Internet.</target>       </trans-unit>
      </group>
    </body>
  </file>
</xliff>